unicms_editorial_board/__init__.py
unicms_editorial_board/apps.py
unicms_editorial_board/urls.py
unicms_editorial_board/views.py
unicms_editorial_board/static/unicms_editorial_board_vue/Dashboard.PNG
unicms_editorial_board/static/unicms_editorial_board_vue/favicon.png
unicms_editorial_board/static/unicms_editorial_board_vue/manifest.json
unicms_editorial_board/static/unicms_editorial_board_vue/precache-manifest.6e8c67fb1936fa6a48804fbec5c337f5.js
unicms_editorial_board/static/unicms_editorial_board_vue/robots.txt
unicms_editorial_board/static/unicms_editorial_board_vue/service-worker.js
unicms_editorial_board/static/unicms_editorial_board_vue/css/app.bca404fa.css
unicms_editorial_board/static/unicms_editorial_board_vue/css/chunk-vendors.25bdde32.css
unicms_editorial_board/static/unicms_editorial_board_vue/img/default-avatar.png
unicms_editorial_board/static/unicms_editorial_board_vue/img/favicon.ico
unicms_editorial_board/static/unicms_editorial_board_vue/img/favicon.png
unicms_editorial_board/static/unicms_editorial_board_vue/img/loading-bubbles.svg
unicms_editorial_board/static/unicms_editorial_board_vue/img/mask.png
unicms_editorial_board/static/unicms_editorial_board_vue/img/new_logo.png
unicms_editorial_board/static/unicms_editorial_board_vue/img/sidebar-1.jpg
unicms_editorial_board/static/unicms_editorial_board_vue/img/sidebar-2.jpg
unicms_editorial_board/static/unicms_editorial_board_vue/img/sidebar-3.jpg
unicms_editorial_board/static/unicms_editorial_board_vue/img/sidebar-4.jpg
unicms_editorial_board/static/unicms_editorial_board_vue/img/sidebar-5.jpg
unicms_editorial_board/static/unicms_editorial_board_vue/img/tim_80x80.png
unicms_editorial_board/static/unicms_editorial_board_vue/img/vue-logo.png
unicms_editorial_board/static/unicms_editorial_board_vue/img/faces/face-0.jpg
unicms_editorial_board/static/unicms_editorial_board_vue/img/faces/face-1.jpg
unicms_editorial_board/static/unicms_editorial_board_vue/img/faces/face-2.jpg
unicms_editorial_board-0.25.1.dist-info/AUTHORS
unicms_editorial_board-0.25.1.dist-info/LICENSE
unicms_editorial_board-0.25.1.dist-info/METADATA
unicms_editorial_board-0.25.1.dist-info/WHEEL
unicms_editorial_board-0.25.1.dist-info/top_level.txt
unicms_editorial_board-0.25.1.dist-info/RECORD
