Metadata-Version: 2.1
Name: unicms-editorial-board
Version: 0.25.1
Summary: Vue.js + Bootstrap Editorial Board for uniCMS
Home-page: https://github.com/UniversitaDellaCalabria/unicms-editorial-board
Author: Giuseppe De Marco, Francesco Filicetti
Author-email: giuseppe.demarco@unical.it, francesco.filicetti@unical.it
License: Apache License 2.0
Platform: UNKNOWN
Classifier: Environment :: Web Environment
Classifier: Framework :: Django
Classifier: Framework :: Django :: 2.0
Classifier: Framework :: Django :: 3.0
Classifier: Intended Audience :: Developers
Classifier: License :: OSI Approved :: Apache Software License
Classifier: Operating System :: OS Independent
Classifier: Programming Language :: Python
Classifier: Programming Language :: Python :: 3
License-File: LICENSE
License-File: AUTHORS
Requires-Dist: django (<4.0,>=2.0)
